mkits/__init__.py
mkits/boltz.py
mkits/builder.py
mkits/critic2.py
mkits/database.py
mkits/fdmnes.py
mkits/globle.py
mkits/gui.py
mkits/main.py
mkits/qe.py
mkits/structgen.py
mkits/sysfc.py
mkits/test.py
mkits/vasp.py
mkits/wien.py
mkits-0.90.dist-info/LICENSE
mkits-0.90.dist-info/METADATA
mkits-0.90.dist-info/WHEEL
mkits-0.90.dist-info/entry_points.txt
mkits-0.90.dist-info/top_level.txt
mkits-0.90.dist-info/RECORD
